setup.cfg
setup.py
charc/__init__.py
charc/nn.py
charc/old_test.py
charc/old_train.py
charc/resources.py
charc.egg-info/PKG-INFO
charc.egg-info/SOURCES.txt
charc.egg-info/dependency_links.txt
charc.egg-info/requires.txt
charc.egg-info/top_level.txt