Metadata-Version: 1.0
Name: charc
Version: 0.01
Summary: Command-line interface to easily train and test character classification ML
Home-page: https://github.com/h3y4w/charc
Author: Heyaw Meteke
Author-email: UNKNOWN
License: UNKNOWN
Platform: UNKNOWN
